CHANGELOG
MANIFEST.in
README.rst
requirements.txt
setup.py
hazel/__init__.py
hazel/build.py
hazel/cli.py
hazel/config.py
hazel/deploy.py
hazel/load.py
hazel/utils.py
hazel.egg-info/PKG-INFO
hazel.egg-info/SOURCES.txt
hazel.egg-info/dependency_links.txt
hazel.egg-info/entry_points.txt
hazel.egg-info/requires.txt
hazel.egg-info/top_level.txt
hazel/default/.DS_Store
hazel/default/config.yml