Metadata-Version: 1.0
Name: hazel
Version: 0.4.5
Summary: hazel: a capsule static blog generator
Home-page: https://github.com/shunfan/hazel
Author: Shunfan Du
Author-email: i@perry.asia
License: MIT
Keywords: blog markdown static rsync
Platform: UNKNOWN
Classifier: Development Status :: 3 - Alpha
Classifier: Environment :: Console
Classifier: Intended Audience :: Developers
Classifier: License :: OSI Approved :: MIT License
Classifier: Natural Language :: English
Classifier: Operating System :: MacOS
Classifier: Operating System :: POSIX :: Linux
Classifier: Programming Language :: Python :: 2.6
Classifier: Programming Language :: Python :: 2.7
Classifier: Programming Language :: Python :: 3.2
Classifier: Programming Language :: Python :: 3.3
